{
  "settings": [
    {
      "name": 0,
      "height": 480,
      "gridSize": 32,
      "width": 320
    },
    {
      "name": 1,
      "ropePhysicsSpeed": 1,
      "special": 2,
      "nightLevel": false
    }
  ],
  "objects": [
    {
      "name": 4,
      "x": 364,
      "y": 126,
      "locale": "en",
      "text": "Eating candies! I love this game! Gaming together!",
      "width": 160,
      "height": 60
    },
    {
      "name": 4,
      "x": 364,
      "y": 126,
      "locale": "ru",
      "text": "Есть конфеты! Я люблю эту игру! Играем вместе!",
      "width": 160,
      "height": 60
    },
    {
      "name": 4,
      "x": 364,
      "y": 126,
      "locale": "de",
      "text": "Süßigkeiten essen! Ich liebe dieses Spiel! Zusammen spielen!",
      "width": 160,
      "height": 60
    },
    {
      "name": 4,
      "x": 364,
      "y": 126,
      "locale": "fr",
      "text": "Manger des bonbons ! J'adore ce jeu ! Jouons ensemble !",
      "width": 160,
      "height": 60
    },
    {
      "name": 4,
      "x": 364,
      "y": 126,
      "locale": "es",
      "text": "¡Comer dulces! ¡Me encanta este juego! ¡Jugar juntos!",
      "width": 160,
      "height": 60
    },
    {
      "name": 4,
      "x": 364,
      "y": 126,
      "locale": "it",
      "text": "Mangiare caramelle! Amo questo gioco! Giochiamo insieme!",
      "width": 160,
      "height": 60
    },
    {
      "name": 4,
      "x": 364,
      "y": 126,
      "locale": "nl",
      "text": "Snoep eten! Ik hou van dit spel! Samen spelen!",
      "width": 160,
      "height": 60
    },
    {
      "name": 4,
      "x": 364,
      "y": 126,
      "locale": "pt",
      "text": "Comer doces! Eu amo este jogo! Jogando juntos!",
      "width": 160,
      "height": 60
    },
    {
      "name": 4,
      "x": 364,
      "y": 126,
      "locale": "ko",
      "text": "사탕 먹기! 이 게임 정말 좋아! 같이 게임하자!",
      "width": 160,
      "height": 60
    },
    {
      "name": 4,
      "x": 364,
      "y": 126,
      "locale": "ja",
      "text": "キャンディを食べよう！このゲーム大好き！一緒に遊ぼう！",
      "width": 160,
      "height": 60
    },
    {
      "name": 4,
      "x": 364,
      "y": 126,
      "locale": "zh",
      "text": "吃糖果！我喜欢这个游戏！一起玩吧！",
      "width": 160,
      "height": 60
    },
    {
      "name": 4,
      "x": 364,
      "y": 126,
      "locale": "zh-TW",
      "text": "吃糖果！我喜歡這個遊戲！一起玩吧！",
      "width": 160,
      "height": 60
    },
    {
      "name": 4,
      "x": 142,
      "y": 397,
      "locale": "en",
      "text": "Magic hat and mouse",
      "width": 160,
      "height": 60
    },
    {
      "name": 4,
      "x": 142,
      "y": 397,
      "locale": "ru",
      "text": "Волшебная шляпа и мышь",
      "width": 160,
      "height": 60
    },
    {
      "name": 4,
      "x": 142,
      "y": 397,
      "locale": "de",
      "text": "Zauberhut und Maus",
      "width": 160,
      "height": 60
    },
    {
      "name": 4,
      "x": 142,
      "y": 397,
      "locale": "fr",
      "text": "Chapeau magique et souris",
      "width": 160,
      "height": 60
    },
    {
      "name": 4,
      "x": 142,
      "y": 397,
      "locale": "es",
      "text": "Sombrero mágico y ratón",
      "width": 160,
      "height": 60
    },
    {
      "name": 4,
      "x": 142,
      "y": 397,
      "locale": "it",
      "text": "Cappello magico e topo",
      "width": 160,
      "height": 60
    },
    {
      "name": 4,
      "x": 142,
      "y": 397,
      "locale": "nl",
      "text": "Magische hoed en muis",
      "width": 160,
      "height": 60
    },
    {
      "name": 4,
      "x": 142,
      "y": 397,
      "locale": "pt",
      "text": "Chapéu mágico e rato",
      "width": 160,
      "height": 60
    },
    {
      "name": 4,
      "x": 142,
      "y": 397,
      "locale": "ko",
      "text": "마법 모자와 쥐",
      "width": 160,
      "height": 60
    },
    {
      "name": 4,
      "x": 142,
      "y": 397,
      "locale": "ja",
      "text": "魔法の帽子とネズミ",
      "width": 160,
      "height": 60
    },
    {
      "name": 4,
      "x": 142,
      "y": 397,
      "locale": "zh",
      "text": "魔法帽子和老鼠",
      "width": 160,
      "height": 60
    },
    {
      "name": 4,
      "x": 142,
      "y": 397,
      "locale": "zh-TW",
      "text": "魔法帽子和老鼠",
      "width": 160,
      "height": 60
    },
    {
      "name": 4,
      "x": -100,
      "y": 248,
      "locale": "en",
      "text": "Cut the rope",
      "width": 160,
      "height": 60
    },
    {
      "name": 4,
      "x": -100,
      "y": 248,
      "locale": "ru",
      "text": "Разрежь верёвку",
      "width": 160,
      "height": 60
    },
    {
      "name": 4,
      "x": -100,
      "y": 248,
      "locale": "de",
      "text": "Schneide das Seil",
      "width": 160,
      "height": 60
    },
    {
      "name": 4,
      "x": -100,
      "y": 248,
      "locale": "fr",
      "text": "Coupe la corde",
      "width": 160,
      "height": 60
    },
    {
      "name": 4,
      "x": -100,
      "y": 248,
      "locale": "es",
      "text": "Corta la cuerda",
      "width": 160,
      "height": 60
    },
    {
      "name": 4,
      "x": -100,
      "y": 248,
      "locale": "it",
      "text": "Taglia la corda",
      "width": 160,
      "height": 60
    },
    {
      "name": 4,
      "x": -100,
      "y": 248,
      "locale": "nl",
      "text": "Snijd het touw door",
      "width": 160,
      "height": 60
    },
    {
      "name": 4,
      "x": -100,
      "y": 248,
      "locale": "pt",
      "text": "Corte a corda",
      "width": 160,
      "height": 60
    },
    {
      "name": 4,
      "x": -100,
      "y": 248,
      "locale": "ko",
      "text": "줄을 자르세요",
      "width": 160,
      "height": 60
    },
    {
      "name": 4,
      "x": -100,
      "y": 248,
      "locale": "ja",
      "text": "ロープを切ろう",
      "width": 160,
      "height": 60
    },
    {
      "name": 4,
      "x": -100,
      "y": 248,
      "locale": "zh",
      "text": "剪断绳子",
      "width": 160,
      "height": 60
    },
    {
      "name": 4,
      "x": -100,
      "y": 248,
      "locale": "zh-TW",
      "text": "剪斷繩子",
      "width": 160,
      "height": 60
    },
    {
      "name": 14,
      "x": -24,
      "y": 261,
      "locale": "en",
      "special": 2,
      "rotateSpeed": 100
    },
    {
      "name": 5,
      "x": -35,
      "y": 248,
      "locale": "en"
    },
    {
      "name": 3,
      "x": 442,
      "y": 257,
      "timeout": -1
    },
    {
      "name": 3,
      "x": 230,
      "y": 260,
      "timeout": -1
    },
    {
      "name": 3,
      "x": 34,
      "y": 210,
      "timeout": -1
    },
    {
      "name": 2,
      "x": 442,
      "y": 361
    },
    {
      "name": 56,
      "x": 97,
      "y": 204,
      "angle": 180,
      "group": 0
    },
    {
      "name": 56,
      "x": 226,
      "y": 174,
      "angle": 90,
      "group": 0
    },
    {
      "name": 133,
      "x": 442,
      "y": 89,
      "angle": 180,
      "activeTime": 1,
      "radius": 50,
      "index": 2
    },
    {
      "name": 133,
      "x": 227,
      "y": 358,
      "angle": 0,
      "activeTime": 1,
      "radius": 50,
      "index": 1
    },
    {
      "name": 100,
      "x": 13,
      "y": 303,
      "spider": false,
      "gun": false,
      "wheel": false,
      "part": "L",
      "hidePath": false,
      "moveOffset": 0,
      "moveVertical": false,
      "length": 50,
      "moveLength": -1,
      "radius": -1,
      "kickable": false,
      "kicked": false,
      "invisible": false,
      "helicopter": false,
      "bindBulb": false
    },
    {
      "name": 100,
      "x": 9,
      "y": 117,
      "spider": false,
      "gun": false,
      "wheel": false,
      "part": "L",
      "hidePath": false,
      "moveOffset": 0,
      "moveVertical": false,
      "length": 50,
      "moveLength": -1,
      "radius": -1,
      "kickable": false,
      "kicked": false,
      "invisible": false,
      "helicopter": false,
      "bindBulb": false
    },
    {
      "name": 52,
      "x": -76,
      "y": 206
    }
  ]
}
